pan_cortex_data_lake/__init__.py
pan_cortex_data_lake/credentials.py
pan_cortex_data_lake/exceptions.py
pan_cortex_data_lake/httpclient.py
pan_cortex_data_lake/query.py
pan_cortex_data_lake/utils.py
pan_cortex_data_lake/adapters/__init__.py
pan_cortex_data_lake/adapters/adapter.py
pan_cortex_data_lake/adapters/tinydb_adapter.py
pan_cortex_data_lake-2.0.0a14.dist-info/AUTHORS.md
pan_cortex_data_lake-2.0.0a14.dist-info/LICENSE
pan_cortex_data_lake-2.0.0a14.dist-info/METADATA
pan_cortex_data_lake-2.0.0a14.dist-info/WHEEL
pan_cortex_data_lake-2.0.0a14.dist-info/top_level.txt
pan_cortex_data_lake-2.0.0a14.dist-info/RECORD
