Metadata-Version: 2.1
Name: pan-cortex-data-lake
Version: 2.0.0a14
Summary: Python idiomatic SDK for Cortex™ Data Lake.
Home-page: https://github.com/PaloAltoNetworks/pan-cortex-data-lake-python
Author: Steven Serrata
Author-email: sserrata@paloaltonetworks.com
License: ISC license
Keywords: cortex data lake
Platform: UNKNOWN
Classifier: Development Status :: 3 - Alpha
Classifier: Intended Audience :: Developers
Classifier: License :: OSI Approved :: ISC License (ISCL)
Classifier: Natural Language :: English
Classifier: Programming Language :: Python :: 2
Classifier: Programming Language :: Python :: 2.7
Classifier: Programming Language :: Python :: 3
Classifier: Programming Language :: Python :: 3.5
Classifier: Programming Language :: Python :: 3.6
Classifier: Programming Language :: Python :: 3.7
Classifier: Programming Language :: Python :: 3.8
Requires-Dist: certifi (==2019.11.28)
Requires-Dist: chardet (==3.0.4)
Requires-Dist: requests (==2.23.0)
Requires-Dist: tinydb (==3.15.2)
Requires-Dist: urllib3 (==1.25.8)
